hyperfastuv/__cli__.py
hyperfastuv/__init__.py
hyperfastuv/_version.py
hyperfastuv/py.typed
hyperfastuv/conf/about/hyperfastpy.yaml
hyperfastuv/conf/about/hyperfastuv.yaml
hyperfast_uv_template-0.4.1.dist-info/METADATA
hyperfast_uv_template-0.4.1.dist-info/WHEEL
hyperfast_uv_template-0.4.1.dist-info/entry_points.txt
hyperfast_uv_template-0.4.1.dist-info/licenses/LICENSE
hyperfast_uv_template-0.4.1.dist-info/RECORD
