Metadata-Version: 2.4
Name: hyperfast-uv-template
Version: 0.4.1
Summary: Streamlining Python Project Development with a Comprehensive Toolset for Quality, Efficiency, and Maintainability
Project-URL: Homepage, https://hyperfast-uv.entelecheia.ai
Project-URL: Repository, https://github.com/entelecheia/hyperfast-uv-template
Project-URL: Documentation, https://hyperfast-uv.entelecheia.ai
Author-email: Young Joon Lee <entelecheia@hotmail.com>
License-Expression: MIT
License-File: LICENSE
Keywords: python
Classifier: Intended Audience :: Developers
Classifier: Programming Language :: Python
Classifier: Programming Language :: Python :: 3
Classifier: Programming Language :: Python :: 3.9
Classifier: Programming Language :: Python :: 3.10
Classifier: Programming Language :: Python :: 3.11
Classifier: Programming Language :: Python :: 3.12
Classifier: Programming Language :: Python :: 3.13
Classifier: Topic :: Software Development :: Libraries :: Python Modules
Requires-Python: <4.0,>=3.9
Requires-Dist: click>=8.1.7
